mediawiki_langcodes/__init__.py
mediawiki_langcodes/convert.py
mediawiki_langcodes/langcodes.db
mediawiki_langcodes/py.typed
mediawiki_langcodes-0.2.17.dist-info/licenses/LICENSE
mediawiki_langcodes-0.2.17.dist-info/METADATA
mediawiki_langcodes-0.2.17.dist-info/WHEEL
mediawiki_langcodes-0.2.17.dist-info/top_level.txt
mediawiki_langcodes-0.2.17.dist-info/RECORD
