Metadata-Version: 2.4
Name: mediawiki_langcodes
Version: 0.2.17
Summary: Convert MediaWiki language names and codes
Author: xxyzz
License-Expression: GPL-3.0-or-later
Project-URL: Homepage, https://github.com/xxyzz/mediawiki_langcodes
Project-URL: Repository, https://github.com/xxyzz/mediawiki_langcodes.git
Project-URL: Issues, https://github.com/xxyzz/mediawiki_langcodes/issues
Classifier: Programming Language :: Python :: 3
Classifier: Operating System :: OS Independent
Requires-Python: >=3.10
License-File: LICENSE
Provides-Extra: dev
Requires-Dist: lxml; extra == "dev"
Requires-Dist: mypy; extra == "dev"
Requires-Dist: requests; extra == "dev"
Requires-Dist: ruff; extra == "dev"
Requires-Dist: types-requests; extra == "dev"
Requires-Dist: build; extra == "dev"
Dynamic: license-file
